{
    "metadata": {
        "name": "FactorAnalysis/classification/default",
        "data_type": "tabular",
        "task_type": "classification"
    },
    "validation": {
        "dataset": "iris",
        "context": {}
    },
    "primitives": [
        "sklearn.decomposition.DictionaryLearning",
        "sklearn.decomposition.FactorAnalysis",
        "sklearn.preprocessing.StandardScaler",
        "sklearn.ensemble.RandomForestClassifier"
    ],
    "hyperparameters": {
        "sklearn.decomposition.FactorAnalysis#1": {}
    }
}
